TrafficLite/TrafficLite.v
module TrafficLite (EWCar, NSCar, EWLite, NSLite, clock);

input EWCar, NSCar, clock;
output EWLite, NSLite;

reg state;
initial state = 0;

assign NSLite = ~state;
assign EWLite = state;

always @(posedge clock)
    case(state)
        0: state = EWCar;
        1: state = NSCar;
    endcase
endmodule

TrafficLite/TrafficLite_tb.v
`include "TrafficLite.v"

module TrafficLite_tb;

reg EWCar, NSCar, clock, state;
wire EWLite, NSLite;

TrafficLite uut (
    .EWCar(EWCar),
    .NSCar(NSCar),
    .clock(clock),
    .EWLite(EWLite),
    .NSLite(NSLite)
);

initial 
    begin
        $dumpfile("TrafficLite.vcd");
        $dumpvars(0, TrafficLite_tb);
        NSCar = 0; EWCar = 0; clock = 1;

        #60;
        NSCar = 0; EWCar = 1;

        #60;
        NSCar = 1; EWCar = 0;

        #60;
        NSCar = 1; EWCar = 1;

        #60;
        NSCar = 0; EWCar = 0;

        #60;
        NSCar = 0; EWCar = 1;

        #60;
        NSCar = 1; EWCar = 0;

        #60;
        NSCar = 1; EWCar = 1;

        #60;
        NSCar = 0; EWCar = 0;

        #60;

        $finish;
    end

always
    #30 clock = ~clock;
endmodule

TrafficLite/TrafficLite.vcd
$date
	Mon Oct 17 18:37:55 2022
$end
$version
	Icarus Verilog
$end
$timescale
	1s
$end
$scope module TrafficLite_tb $end
$var wire 1 ! NSLite $end
$var wire 1 " EWLite $end
$var reg 1 # EWCar $end
$var reg 1 $ NSCar $end
$var reg 1 % clock $end
$scope module uut $end
$var wire 1 # EWCar $end
$var wire 1 " EWLite $end
$var wire 1 $ NSCar $end
$var wire 1 ! NSLite $end
$var wire 1 % clock $end
$var reg 1 & state $end
$upscope $end
$upscope $end
$enddefinitions $end
$comment Show the parameter values. $end
$dumpall
$end
#0
$dumpvars
0&
1%
0$
0#
0"
1!
$end
#30
0%
#60
0!
1"
1&
1%
1#
#90
0%
#120
1%
0#
1$
#150
0%
#180
1%
1#
#210
0%
#240
1!
0"
0&
1%
0#
0$
#270
0%
#300
0!
1"
1&
1%
1#
#330
0%
#360
1%
0#
1$
#390
0%
#420
1%
1#
#450
0%
#480
1!
0"
0&
1%
0#
0$
